py_pkg/__init__.py
py_pkg/__version__.py
py_pkg/curves.py
py_pkg/entry_points.py
py_package_template-0.2.0.dist-info/LICENSE
py_package_template-0.2.0.dist-info/METADATA
py_package_template-0.2.0.dist-info/WHEEL
py_package_template-0.2.0.dist-info/entry_points.txt
py_package_template-0.2.0.dist-info/top_level.txt
py_package_template-0.2.0.dist-info/RECORD
