Metadata-Version: 2.1
Name: py-package-template
Version: 0.2.0
Summary: py-package-template - Package Template Project Generator
Home-page: https://github.com/AlexIoannides/py-package-template
Author: Alex Ioannides
Author-email: alex.ioannides@yahoo.co.uk
License: Apache 2.0
Keywords: package development template
Platform: UNKNOWN
Classifier: Development Status :: 4 - Beta
Classifier: Intended Audience :: Developers
Classifier: Programming Language :: Python :: 3.7
Requires-Python: >=3.7.*
Requires-Dist: numpy
Requires-Dist: requests
